enginomics/__init__.py
enginomics/amortization.py
enginomics/cashflow.py
enginomics-0.8.4.dist-info/licenses/LICENSE
enginomics-0.8.4.dist-info/METADATA
enginomics-0.8.4.dist-info/WHEEL
enginomics-0.8.4.dist-info/top_level.txt
enginomics-0.8.4.dist-info/RECORD
