Metadata-Version: 2.4
Name: Enginomics
Version: 0.8.4
Summary: A Python package for engineering economic decision-making
Author-email: Wayne Matthew Syvinski <enginomics@engihelp.net>
License-Expression: Apache-2.0
Classifier: Programming Language :: Python :: 3
Classifier: Operating System :: OS Independent
Classifier: Development Status :: 4 - Beta
Requires-Python: >=3.9
License-File: LICENSE
Requires-Dist: matplotlib
Requires-Dist: numpy
Requires-Dist: numpy-financial
Requires-Dist: pandas
Requires-Dist: pandasql
Requires-Dist: seaborn
Dynamic: license-file
